migrations/0001_initial.py
migrations/0002_alter_metatag_name_alter_opengraphmeta_property_and_more.py
migrations/__init__.py
templatetags/__init__.py
templatetags/seo_tags.py
djangocms_seo-0.1.2.dist-info/LICENSE
djangocms_seo-0.1.2.dist-info/METADATA
djangocms_seo-0.1.2.dist-info/WHEEL
djangocms_seo-0.1.2.dist-info/top_level.txt
djangocms_seo-0.1.2.dist-info/RECORD
