Metadata-Version: 2.1
Name: djangocms-seo
Version: 0.1.2
Summary: A Django CMS extension to manage SEO meta tags for web pages.
Home-page: https://github.com/YessineBR/djangocms_seo
Author: Yessine Ben Rhouma
Author-email: Yasyn Ben Rhouma <ben.rhouma.yessine0610@gmail.com>
License: MIT
Classifier: Environment :: Web Environment
Classifier: Framework :: Django
Classifier: Framework :: Django :: 5.1
Classifier: Framework :: Django CMS
Classifier: Intended Audience :: Developers
Classifier: License :: OSI Approved :: BSD License
Classifier: Operating System :: OS Independent
Classifier: Programming Language :: Python
Classifier: Programming Language :: Python :: 3
Classifier: Programming Language :: Python :: 3 :: Only
Classifier: Programming Language :: Python :: 3.10
Classifier: Programming Language :: Python :: 3.11
Classifier: Programming Language :: Python :: 3.12
Classifier: Topic :: Internet :: WWW/HTTP
Classifier: Topic :: Internet :: WWW/HTTP :: Dynamic Content
Classifier: Topic :: Software Development :: Libraries :: Python Modules
Requires-Python: >=3.10
License-File: LICENSE
Requires-Dist: django>=5.1
Requires-Dist: django-cms>=4.1
